pysagereader/__init__.py
pysagereader/_version.py
pysagereader/make_netcdf.py
pysagereader/sage_ii_reader.py
pysagereader-0.3.1.dist-info/LICENSE
pysagereader-0.3.1.dist-info/METADATA
pysagereader-0.3.1.dist-info/WHEEL
pysagereader-0.3.1.dist-info/top_level.txt
pysagereader-0.3.1.dist-info/RECORD
