Metadata-Version: 2.1
Name: pysagereader
Version: 0.3.1
Summary: SAGE II v7.0 binary file reader
Home-page: https://github.com/LandonRieger/pySAGE.git
Author: USASK ARG
Author-email: landon.rieger@usask.ca
License: MIT
Platform: UNKNOWN
Requires-Python: >=3.6
License-File: LICENSE
Requires-Dist: numpy
Requires-Dist: pandas
Requires-Dist: xarray
Requires-Dist: click
